{
  "videoId": "2D2TLWLu43Q",
  "category": "entertainment",
  "title": "Host Nikki Glaser is \"Golden\"",
  "seriesId": "award-shows",
  "sentenceCount": 10,
  "taggedCount": 10,
  "sentences": [
    {
      "id": "2D2TLWLu43Q-0",
      "en": "It's so viral.",
      "ko": "정말 화제야.",
      "tags": {
        "functions": [
          "F01"
        ],
        "situation": "S34",
        "cefr": "A2",
        "register": "R4",
        "emotions": [
          "E09"
        ],
        "expression_types": [
          "X08"
        ],
        "vibe": "V10",
        "power": [],
        "grammar_intent": [],
        "flags": []
      }
    },
    {
      "id": "2D2TLWLu43Q-1",
      "en": "They asked me to host the Golden Globes They said do your thing, just please don't",
      "ko": "그들이 나에게 골든 글로브를 진행해 달라고 했어. 내 방식대로 해달라고, 제발.",
      "tags": {
        "functions": [
          "F03"
        ],
        "situation": "S34",
        "cefr": "B1",
        "register": "R4",
        "emotions": [
          "E09"
        ],
        "expression_types": [
          "X08"
        ],
        "vibe": "V10",
        "power": [],
        "grammar_intent": [],
        "flags": []
      }
    },
    {
      "id": "2D2TLWLu43Q-2",
      "en": "sing But I had a dream like Marty Supreme",
      "ko": "노래는 부르지 말라고 했지. 하지만 나는 마르티 슈프림처럼 꿈을 꿨어.",
      "tags": {
        "functions": [
          "F09"
        ],
        "situation": "S34",
        "cefr": "B1",
        "register": "R4",
        "emotions": [
          "E09"
        ],
        "expression_types": [
          "X08"
        ],
        "vibe": "V10",
        "power": [],
        "grammar_intent": [],
        "flags": []
      }
    },
    {
      "id": "2D2TLWLu43Q-3",
      "en": "They said no, unless you get Gwyneth Paltrow So I tracked down Goof, showed up on her",
      "ko": "그들은 안 된다고 했어, 그웬 스테파니가 아니면. 그래서 구프를 추적해서 그녀의 집 앞에 나타났어.",
      "tags": {
        "functions": [
          "F03"
        ],
        "situation": "S34",
        "cefr": "B1",
        "register": "R4",
        "emotions": [
          "E09"
        ],
        "expression_types": [
          "X08"
        ],
        "vibe": "V10",
        "power": [],
        "grammar_intent": [],
        "flags": []
      }
    },
    {
      "id": "2D2TLWLu43Q-4",
      "en": "stoop She called the cops, so I'll go it alone",
      "ko": "그녀가 경찰을 불렀고, 나는 혼자서 할 거야.",
      "tags": {
        "functions": [
          "F09"
        ],
        "situation": "S34",
        "cefr": "B1",
        "register": "R4",
        "emotions": [
          "E09"
        ],
        "expression_types": [
          "X08"
        ],
        "vibe": "V10",
        "power": [],
        "grammar_intent": [],
        "flags": []
      }
    },
    {
      "id": "2D2TLWLu43Q-5",
      "en": "So I'm here singing, still committing Just like Chalamet",
      "ko": "그래서 나는 여기서 노래를 부르고 있어, 여전히 헌신하고 있어. 샬라메처럼.",
      "tags": {
        "functions": [
          "F09"
        ],
        "situation": "S34",
        "cefr": "B1",
        "register": "R4",
        "emotions": [
          "E09"
        ],
        "expression_types": [
          "X08"
        ],
        "vibe": "V10",
        "power": [],
        "grammar_intent": [],
        "flags": []
      }
    },
    {
      "id": "2D2TLWLu43Q-6",
      "en": "If Cavalierie Spanx is my Riri, I'll turn around and say",
      "ko": "만약 카발리에 스팽크스가 내 리리라면, 나는 돌아서서 말할 거야.",
      "tags": {
        "functions": [
          "F09"
        ],
        "situation": "S34",
        "cefr": "B1",
        "register": "R4",
        "emotions": [
          "E09"
        ],
        "expression_types": [
          "X08"
        ],
        "vibe": "V10",
        "power": [],
        "grammar_intent": [],
        "flags": []
      }
    },
    {
      "id": "2D2TLWLu43Q-7",
      "en": "I won't give up, up, up on this song, yeah",
      "ko": "이 노래를 절대 포기하지 않을 거야.",
      "tags": {
        "functions": [
          "F09"
        ],
        "situation": "S34",
        "cefr": "B1",
        "register": "R4",
        "emotions": [
          "E09"
        ],
        "expression_types": [
          "X08"
        ],
        "vibe": "V10",
        "power": [],
        "grammar_intent": [],
        "flags": []
      }
    },
    {
      "id": "2D2TLWLu43Q-8",
      "en": "If you like this song, yeah",
      "ko": "이 노래가 마음에 든다면, 응.",
      "tags": {
        "functions": [
          "F06"
        ],
        "situation": "S34",
        "cefr": "A2",
        "register": "R4",
        "emotions": [
          "E09"
        ],
        "expression_types": [
          "X08"
        ],
        "vibe": "V10",
        "power": [],
        "grammar_intent": [],
        "flags": []
      }
    },
    {
      "id": "2D2TLWLu43Q-9",
      "en": "Stop! Stop! Please! Stop! Stop!",
      "ko": "그만해! 그만해! 제발! 그만해! 그만해!",
      "tags": {
        "functions": [
          "F35"
        ],
        "situation": "S34",
        "cefr": "A2",
        "register": "R4",
        "emotions": [
          "E09"
        ],
        "expression_types": [
          "X08"
        ],
        "vibe": "V10",
        "power": [],
        "grammar_intent": [],
        "flags": []
      }
    }
  ]
}
