{
  "videoId": "_JZom_gVfuw",
  "category": "music",
  "title": "The Notorious B.I.G. - Juicy [4K]",
  "seriesId": "hip-hop-classics",
  "sentenceCount": 20,
  "taggedCount": 20,
  "sentences": [
    {
      "id": "_JZom_gVfuw-0",
      "en": "Every Saturday, Rap Attack, Mr. Magic, Molly Maul",
      "ko": "매주 토요일, 랩 어택, 미스터 매직, 몰리 몰",
      "tags": {
        "functions": [
          "F01"
        ],
        "situation": "S46",
        "cefr": "A2",
        "register": "R4",
        "emotions": [
          "E09"
        ],
        "expression_types": [
          "X08"
        ],
        "vibe": "V18",
        "power": [],
        "grammar_intent": [],
        "flags": [
          "is_lyrics"
        ]
      }
    },
    {
      "id": "_JZom_gVfuw-1",
      "en": "I let my tape rock till my tape pop",
      "ko": "내 테이프가 터질 때까지 틀어놨어",
      "tags": {
        "functions": [
          "F01"
        ],
        "situation": "S46",
        "cefr": "A2",
        "register": "R4",
        "emotions": [
          "E09"
        ],
        "expression_types": [
          "X08"
        ],
        "vibe": "V18",
        "power": [],
        "grammar_intent": [],
        "flags": [
          "is_lyrics"
        ]
      }
    },
    {
      "id": "_JZom_gVfuw-2",
      "en": "Smokin' weed and bamboo, sippin' on private stock",
      "ko": "대마초 피우고, 프라이빗 스톡 마셔",
      "tags": {
        "functions": [
          "F01"
        ],
        "situation": "S46",
        "cefr": "A2",
        "register": "R4",
        "emotions": [
          "E09"
        ],
        "expression_types": [
          "X08"
        ],
        "vibe": "V18",
        "power": [],
        "grammar_intent": [],
        "flags": [
          "is_lyrics"
        ]
      }
    },
    {
      "id": "_JZom_gVfuw-3",
      "en": "Way back when I had the red and black lumberjack With the hat to match Remember rappin' Duke? Da-ha, da-ha",
      "ko": "예전에는 빨간색과 검은색의 작업복을 입고 모자도 맞췄지. 기억나? 듀크 랩할 때? 다하, 다하",
      "tags": {
        "functions": [
          "F01"
        ],
        "situation": "S46",
        "cefr": "A2",
        "register": "R4",
        "emotions": [
          "E09"
        ],
        "expression_types": [
          "X08"
        ],
        "vibe": "V18",
        "power": [],
        "grammar_intent": [],
        "flags": [
          "is_lyrics"
        ]
      }
    },
    {
      "id": "_JZom_gVfuw-4",
      "en": "You never thought that hip-hop would take it this far",
      "ko": "힙합이 이렇게 멀리 갈 줄은 몰랐지",
      "tags": {
        "functions": [
          "F01"
        ],
        "situation": "S46",
        "cefr": "A2",
        "register": "R4",
        "emotions": [
          "E09"
        ],
        "expression_types": [
          "X08"
        ],
        "vibe": "V18",
        "power": [],
        "grammar_intent": [],
        "flags": [
          "is_lyrics"
        ]
      }
    },
    {
      "id": "_JZom_gVfuw-5",
      "en": "Now I'm in the limelight cause I rhyme tight",
      "ko": "이제 나는 주목받고 있어, 내 랩이 탄탄하니까",
      "tags": {
        "functions": [
          "F01"
        ],
        "situation": "S46",
        "cefr": "A2",
        "register": "R4",
        "emotions": [
          "E09"
        ],
        "expression_types": [
          "X08"
        ],
        "vibe": "V18",
        "power": [],
        "grammar_intent": [],
        "flags": [
          "is_lyrics"
        ]
      }
    },
    {
      "id": "_JZom_gVfuw-6",
      "en": "Time to get paid, blow up like the World Trade",
      "ko": "돈 벌 시간, 월드 트레이드처럼 터져",
      "tags": {
        "functions": [
          "F01"
        ],
        "situation": "S46",
        "cefr": "A2",
        "register": "R4",
        "emotions": [
          "E09"
        ],
        "expression_types": [
          "X08"
        ],
        "vibe": "V18",
        "power": [],
        "grammar_intent": [],
        "flags": [
          "is_lyrics"
        ]
      }
    },
    {
      "id": "_JZom_gVfuw-7",
      "en": "Born sinner, the opposite of a winner",
      "ko": "태어날 때부터 죄인, 승자의 반대",
      "tags": {
        "functions": [
          "F01"
        ],
        "situation": "S46",
        "cefr": "A2",
        "register": "R4",
        "emotions": [
          "E09"
        ],
        "expression_types": [
          "X08"
        ],
        "vibe": "V18",
        "power": [],
        "grammar_intent": [],
        "flags": [
          "is_lyrics"
        ]
      }
    },
    {
      "id": "_JZom_gVfuw-8",
      "en": "Remember when I used to eat sardines for dinner?",
      "ko": "저녁으로 정어리 먹던 때 기억나?",
      "tags": {
        "functions": [
          "F01"
        ],
        "situation": "S46",
        "cefr": "A2",
        "register": "R4",
        "emotions": [
          "E09"
        ],
        "expression_types": [
          "X08"
        ],
        "vibe": "V18",
        "power": [],
        "grammar_intent": [],
        "flags": [
          "is_lyrics"
        ]
      }
    },
    {
      "id": "_JZom_gVfuw-9",
      "en": "Peace to Rod G, Brucie B, Kid Capri",
      "ko": "로드 G, 브루시 B, 키드 카프리에게 평화",
      "tags": {
        "functions": [
          "F01"
        ],
        "situation": "S46",
        "cefr": "A2",
        "register": "R4",
        "emotions": [
          "E09"
        ],
        "expression_types": [
          "X08"
        ],
        "vibe": "V18",
        "power": [],
        "grammar_intent": [],
        "flags": [
          "is_lyrics"
        ]
      }
    },
    {
      "id": "_JZom_gVfuw-10",
      "en": "Fuck Master Flex, love Buckstar Skeet",
      "ko": "팍 마스터 플렉스, 벅스타 스킷 사랑해",
      "tags": {
        "functions": [
          "F01"
        ],
        "situation": "S46",
        "cefr": "A2",
        "register": "R4",
        "emotions": [
          "E09"
        ],
        "expression_types": [
          "X08"
        ],
        "vibe": "V18",
        "power": [],
        "grammar_intent": [],
        "flags": [
          "is_lyrics",
          "contains_profanity"
        ]
      }
    },
    {
      "id": "_JZom_gVfuw-11",
      "en": "I'm blowin' up like you thought I would",
      "ko": "내가 터질 거라고 생각했지?",
      "tags": {
        "functions": [
          "F01"
        ],
        "situation": "S46",
        "cefr": "A2",
        "register": "R4",
        "emotions": [
          "E09"
        ],
        "expression_types": [
          "X08"
        ],
        "vibe": "V18",
        "power": [],
        "grammar_intent": [],
        "flags": [
          "is_lyrics"
        ]
      }
    },
    {
      "id": "_JZom_gVfuw-12",
      "en": "Call a crib, same number, same hood It's all good",
      "ko": "집에 전화해, 같은 번호, 같은 동네. 모두 괜찮아",
      "tags": {
        "functions": [
          "F01"
        ],
        "situation": "S46",
        "cefr": "A2",
        "register": "R4",
        "emotions": [
          "E09"
        ],
        "expression_types": [
          "X08"
        ],
        "vibe": "V18",
        "power": [],
        "grammar_intent": [],
        "flags": [
          "is_lyrics"
        ]
      }
    },
    {
      "id": "_JZom_gVfuw-13",
      "en": "Uh, yeah",
      "ko": "어, 그래",
      "tags": {
        "functions": [
          "F01"
        ],
        "situation": "S46",
        "cefr": "A2",
        "register": "R4",
        "emotions": [
          "E09"
        ],
        "expression_types": [
          "X08"
        ],
        "vibe": "V18",
        "power": [],
        "grammar_intent": [],
        "flags": [
          "is_lyrics",
          "is_fragment"
        ]
      }
    },
    {
      "id": "_JZom_gVfuw-14",
      "en": "And if you don't know, now you know, nigga",
      "ko": "모르겠다면 이제 알게 됐어, 친구",
      "tags": {
        "functions": [
          "F01"
        ],
        "situation": "S46",
        "cefr": "A2",
        "register": "R4",
        "emotions": [
          "E09"
        ],
        "expression_types": [
          "X08"
        ],
        "vibe": "V18",
        "power": [],
        "grammar_intent": [],
        "flags": [
          "is_lyrics"
        ]
      }
    },
    {
      "id": "_JZom_gVfuw-15",
      "en": "You knew very well who you are",
      "ko": "너 자신이 누구인지 잘 알고 있었지",
      "tags": {
        "functions": [
          "F01"
        ],
        "situation": "S46",
        "cefr": "A2",
        "register": "R4",
        "emotions": [
          "E09"
        ],
        "expression_types": [
          "X08"
        ],
        "vibe": "V18",
        "power": [],
        "grammar_intent": [],
        "flags": [
          "is_lyrics"
        ]
      }
    },
    {
      "id": "_JZom_gVfuw-16",
      "en": "No one holds you down",
      "ko": "아무도 너를 억누르지 않아",
      "tags": {
        "functions": [
          "F01"
        ],
        "situation": "S46",
        "cefr": "A2",
        "register": "R4",
        "emotions": [
          "E09"
        ],
        "expression_types": [
          "X08"
        ],
        "vibe": "V18",
        "power": [],
        "grammar_intent": [],
        "flags": [
          "is_lyrics"
        ]
      }
    },
    {
      "id": "_JZom_gVfuw-17",
      "en": "We saw the star",
      "ko": "우리는 별을 봤어",
      "tags": {
        "functions": [
          "F01"
        ],
        "situation": "S46",
        "cefr": "A1",
        "register": "R4",
        "emotions": [
          "E09"
        ],
        "expression_types": [
          "X08"
        ],
        "vibe": "V18",
        "power": [],
        "grammar_intent": [],
        "flags": [
          "is_lyrics"
        ]
      }
    },
    {
      "id": "_JZom_gVfuw-18",
      "en": "You had it cool when I said my name",
      "ko": "내가 내 이름을 말했을 때 너는 멋졌어",
      "tags": {
        "functions": [
          "F01"
        ],
        "situation": "S46",
        "cefr": "A2",
        "register": "R4",
        "emotions": [
          "E09"
        ],
        "expression_types": [
          "X08"
        ],
        "vibe": "V18",
        "power": [],
        "grammar_intent": [],
        "flags": [
          "is_lyrics"
        ]
      }
    },
    {
      "id": "_JZom_gVfuw-19",
      "en": "Cause you're the only one I give you sudden",
      "ko": "너는 내가 갑자기 주는 유일한 사람이야",
      "tags": {
        "functions": [
          "F01"
        ],
        "situation": "S46",
        "cefr": "A2",
        "register": "R4",
        "emotions": [
          "E09"
        ],
        "expression_types": [
          "X08"
        ],
        "vibe": "V18",
        "power": [],
        "grammar_intent": [],
        "flags": [
          "is_lyrics"
        ]
      }
    }
  ]
}
