{
  "videoId": "i9IA4XFPEnk",
  "category": "drama",
  "title": "Jack's TV Show Pitch",
  "seriesId": "30-rock",
  "sentenceCount": 4,
  "taggedCount": 4,
  "sentences": [
    {
      "id": "i9IA4XFPEnk-0",
      "en": "The moms? What moms?",
      "ko": "엄마들? 어떤 엄마들?",
      "tags": {
        "functions": [
          "F06"
        ],
        "situation": "S09",
        "cefr": "A2",
        "register": "R4",
        "emotions": [
          "E05"
        ],
        "expression_types": [
          "X08"
        ],
        "vibe": "V12",
        "power": [],
        "grammar_intent": [],
        "flags": []
      }
    },
    {
      "id": "i9IA4XFPEnk-1",
      "en": "The staff moms that are going to be on the Mother's Day show",
      "ko": "어버이날 쇼에 나올 스태프 엄마들 말이야.",
      "tags": {
        "functions": [
          "F02"
        ],
        "situation": "S10",
        "cefr": "B1",
        "register": "R4",
        "emotions": [
          "E14"
        ],
        "expression_types": [
          "X08"
        ],
        "vibe": "V10",
        "power": [],
        "grammar_intent": [],
        "flags": [
          "is_narration"
        ]
      }
    },
    {
      "id": "i9IA4XFPEnk-2",
      "en": "that NBC is making us do after their ill-fated decision to re-air the pilot of Bitch Hunter?",
      "ko": "NBC가 'Bitch Hunter' 파일럿을 재방송하기로 한 잘못된 결정 이후에 우리에게 강요하는 거야?",
      "tags": {
        "functions": [
          "F06"
        ],
        "situation": "S09",
        "cefr": "B2",
        "register": "R5",
        "emotions": [
          "E05"
        ],
        "expression_types": [
          "X08"
        ],
        "vibe": "V12",
        "power": [],
        "grammar_intent": [],
        "flags": [
          "contains_profanity"
        ]
      }
    },
    {
      "id": "i9IA4XFPEnk-3",
      "en": "Put the mimosas down, bitch!",
      "ko": "미모사를 내려놔, 이 자식아!",
      "tags": {
        "functions": [
          "F01"
        ],
        "situation": "S09",
        "cefr": "A2",
        "register": "R5",
        "emotions": [
          "E14"
        ],
        "expression_types": [
          "X08"
        ],
        "vibe": "V10",
        "power": [],
        "grammar_intent": [],
        "flags": [
          "contains_profanity"
        ]
      }
    }
  ],
  "transcriptHash": "0b2af060c4db86fb"
}
