{
  "videoId": "ISJpKRTkvpc",
  "category": "entertainment",
  "title": "Caleb Hearon: Model Comedian",
  "seriesId": "standup-comedy",
  "sentenceCount": 23,
  "taggedCount": 23,
  "sentences": [
    {
      "id": "ISJpKRTkvpc-0",
      "en": "The world's on fire, but I'm like,",
      "ko": "세상이 불타고 있지만, 나는 이렇게 생각해,",
      "tags": {
        "functions": [
          "F01"
        ],
        "situation": "S34",
        "cefr": "A2",
        "register": "R4",
        "emotions": [
          "E09"
        ],
        "expression_types": [
          "X06"
        ],
        "vibe": "V10",
        "power": [],
        "grammar_intent": [],
        "flags": []
      }
    },
    {
      "id": "ISJpKRTkvpc-1",
      "en": "let's get silly with it, you know?",
      "ko": "좀 웃겨보자, 알지?",
      "tags": {
        "functions": [
          "F35"
        ],
        "situation": "S34",
        "cefr": "A2",
        "register": "R4",
        "emotions": [
          "E09"
        ],
        "expression_types": [
          "X06"
        ],
        "vibe": "V10",
        "power": [],
        "grammar_intent": [
          "G09"
        ],
        "flags": []
      }
    },
    {
      "id": "ISJpKRTkvpc-2",
      "en": "I came out as bisexual on Facebook.",
      "ko": "나는 페이스북에서 바이섹슈얼로 커밍아웃했어.",
      "tags": {
        "functions": [
          "F01"
        ],
        "situation": "S34",
        "cefr": "A2",
        "register": "R4",
        "emotions": [
          "E09"
        ],
        "expression_types": [
          "X08"
        ],
        "vibe": "V10",
        "power": [],
        "grammar_intent": [],
        "flags": []
      }
    },
    {
      "id": "ISJpKRTkvpc-3",
      "en": "Stop. I don't want to hear it. Stop now.",
      "ko": "그만해. 듣고 싶지 않아. 지금 그만해.",
      "tags": {
        "functions": [
          "F35",
          "F40"
        ],
        "situation": "S34",
        "cefr": "A2",
        "register": "R4",
        "emotions": [
          "E09"
        ],
        "expression_types": [
          "X08"
        ],
        "vibe": "V10",
        "power": [],
        "grammar_intent": [
          "G01",
          "G24"
        ],
        "flags": []
      }
    },
    {
      "id": "ISJpKRTkvpc-4",
      "en": "And I called my dad and I gave him the whole speech.",
      "ko": "아빠에게 전화해서 모든 이야기를 했어.",
      "tags": {
        "functions": [
          "F01"
        ],
        "situation": "S34",
        "cefr": "A2",
        "register": "R4",
        "emotions": [
          "E09"
        ],
        "expression_types": [
          "X08"
        ],
        "vibe": "V10",
        "power": [],
        "grammar_intent": [],
        "flags": []
      }
    },
    {
      "id": "ISJpKRTkvpc-5",
      "en": "He took a long pause and he goes,",
      "ko": "그는 잠시 멈추더니 말했어,",
      "tags": {
        "functions": [
          "F01"
        ],
        "situation": "S34",
        "cefr": "A2",
        "register": "R4",
        "emotions": [
          "E09"
        ],
        "expression_types": [
          "X08"
        ],
        "vibe": "V10",
        "power": [],
        "grammar_intent": [],
        "flags": []
      }
    },
    {
      "id": "ISJpKRTkvpc-6",
      "en": "buddy, if you're just going to come out as full gay",
      "ko": "친구야, 만약 너가 6개월 후에 완전 게이로 커밍아웃할 거라면,",
      "tags": {
        "functions": [
          "F01"
        ],
        "situation": "S34",
        "cefr": "A2",
        "register": "R4",
        "emotions": [
          "E09"
        ],
        "expression_types": [
          "X08"
        ],
        "vibe": "V10",
        "power": [],
        "grammar_intent": [],
        "flags": []
      }
    },
    {
      "id": "ISJpKRTkvpc-7",
      "en": "in six months, can we skip to that part?",
      "ko": "그 부분은 건너뛰면 안 될까?",
      "tags": {
        "functions": [
          "F01"
        ],
        "situation": "S34",
        "cefr": "A2",
        "register": "R4",
        "emotions": [
          "E09"
        ],
        "expression_types": [
          "X08"
        ],
        "vibe": "V10",
        "power": [],
        "grammar_intent": [],
        "flags": []
      }
    },
    {
      "id": "ISJpKRTkvpc-8",
      "en": "Yeah. Yeah, we can.",
      "ko": "응. 응, 괜찮아.",
      "tags": {
        "functions": [
          "F07"
        ],
        "situation": "S34",
        "cefr": "A1",
        "register": "R4",
        "emotions": [
          "E09"
        ],
        "expression_types": [
          "X08"
        ],
        "vibe": "V10",
        "power": [],
        "grammar_intent": [],
        "flags": []
      }
    },
    {
      "id": "ISJpKRTkvpc-9",
      "en": "As a kid, I was so uptight.",
      "ko": "어렸을 때 나는 너무 경직되어 있었어.",
      "tags": {
        "functions": [
          "F01"
        ],
        "situation": "S34",
        "cefr": "A2",
        "register": "R4",
        "emotions": [
          "E09"
        ],
        "expression_types": [
          "X08"
        ],
        "vibe": "V10",
        "power": [],
        "grammar_intent": [],
        "flags": []
      }
    },
    {
      "id": "ISJpKRTkvpc-10",
      "en": "When I was 15, I asked for a business suit.",
      "ko": "15살 때 비즈니스 수트를 요청했어.",
      "tags": {
        "functions": [
          "F01"
        ],
        "situation": "S34",
        "cefr": "A2",
        "register": "R4",
        "emotions": [
          "E09"
        ],
        "expression_types": [
          "X08"
        ],
        "vibe": "V10",
        "power": [
          "P02"
        ],
        "grammar_intent": [],
        "flags": []
      }
    },
    {
      "id": "ISJpKRTkvpc-11",
      "en": "He had no business to speak of.",
      "ko": "그는 사업이 없었어.",
      "tags": {
        "functions": [
          "F01"
        ],
        "situation": "S34",
        "cefr": "A2",
        "register": "R4",
        "emotions": [
          "E09"
        ],
        "expression_types": [
          "X08"
        ],
        "vibe": "V10",
        "power": [],
        "grammar_intent": [],
        "flags": []
      }
    },
    {
      "id": "ISJpKRTkvpc-12",
      "en": "Sorry, I'm bigger than this small town.",
      "ko": "미안, 나는 이 작은 마을보다 더 커.",
      "tags": {
        "functions": [
          "F01"
        ],
        "situation": "S34",
        "cefr": "A2",
        "register": "R4",
        "emotions": [
          "E09"
        ],
        "expression_types": [
          "X08"
        ],
        "vibe": "V10",
        "power": [],
        "grammar_intent": [],
        "flags": []
      }
    },
    {
      "id": "ISJpKRTkvpc-13",
      "en": "I don't respect straight guys as a rule.",
      "ko": "나는 원칙적으로 이성애자를 존중하지 않아.",
      "tags": {
        "functions": [
          "F40"
        ],
        "situation": "S34",
        "cefr": "A2",
        "register": "R4",
        "emotions": [
          "E09"
        ],
        "expression_types": [
          "X08"
        ],
        "vibe": "V10",
        "power": [],
        "grammar_intent": [],
        "flags": []
      }
    },
    {
      "id": "ISJpKRTkvpc-14",
      "en": "The only straight guy I've really ever truly respected",
      "ko": "내가 진정으로 존경했던 유일한 이성애자는",
      "tags": {
        "functions": [
          "F01"
        ],
        "situation": "S34",
        "cefr": "A2",
        "register": "R4",
        "emotions": [
          "E09"
        ],
        "expression_types": [
          "X08"
        ],
        "vibe": "V10",
        "power": [],
        "grammar_intent": [],
        "flags": []
      }
    },
    {
      "id": "ISJpKRTkvpc-15",
      "en": "in my life is a guy I overheard at a bar once.",
      "ko": "한 번 바에서 우연히 들었던 남자야.",
      "tags": {
        "functions": [
          "F01"
        ],
        "situation": "S34",
        "cefr": "A2",
        "register": "R4",
        "emotions": [
          "E09"
        ],
        "expression_types": [
          "X08"
        ],
        "vibe": "V10",
        "power": [],
        "grammar_intent": [],
        "flags": []
      }
    },
    {
      "id": "ISJpKRTkvpc-16",
      "en": "And he goes, no, no, dude, I'm telling you.",
      "ko": "그는 이렇게 말했어, 아니, 아니, 친구야, 내가 말하는 거 들어봐.",
      "tags": {
        "functions": [
          "F01"
        ],
        "situation": "S34",
        "cefr": "A2",
        "register": "R4",
        "emotions": [
          "E09"
        ],
        "expression_types": [
          "X05"
        ],
        "vibe": "V10",
        "power": [
          "P05"
        ],
        "grammar_intent": [],
        "flags": []
      }
    },
    {
      "id": "ISJpKRTkvpc-17",
      "en": "I just tell girls I can't come from blowjobs",
      "ko": "나는 여자들에게 구강 성교로는 오지 못한다고 말해.",
      "tags": {
        "functions": [
          "F01"
        ],
        "situation": "S34",
        "cefr": "A2",
        "register": "R4",
        "emotions": [
          "E09"
        ],
        "expression_types": [
          "X08"
        ],
        "vibe": "V10",
        "power": [],
        "grammar_intent": [],
        "flags": []
      }
    },
    {
      "id": "ISJpKRTkvpc-18",
      "en": "and it makes them want to give me blowjobs even worse.",
      "ko": "그러면 그들이 나에게 구강 성교를 더 하고 싶어해.",
      "tags": {
        "functions": [
          "F01"
        ],
        "situation": "S34",
        "cefr": "A2",
        "register": "R4",
        "emotions": [
          "E09"
        ],
        "expression_types": [
          "X08"
        ],
        "vibe": "V10",
        "power": [],
        "grammar_intent": [
          "G10"
        ],
        "flags": []
      }
    },
    {
      "id": "ISJpKRTkvpc-19",
      "en": "Genius, genius, a beautiful mind montage.",
      "ko": "천재야, 천재, 아름다운 마음의 몽타주.",
      "tags": {
        "functions": [
          "F01"
        ],
        "situation": "S34",
        "cefr": "A1",
        "register": "R4",
        "emotions": [
          "E09"
        ],
        "expression_types": [
          "X08"
        ],
        "vibe": "V10",
        "power": [],
        "grammar_intent": [],
        "flags": []
      }
    },
    {
      "id": "ISJpKRTkvpc-20",
      "en": "I just picture him outside of a nightclub every weekend painting a fence white.",
      "ko": "나는 그가 매주 주말 클럽 밖에서 하얀 울타리를 칠하는 모습을 상상해.",
      "tags": {
        "functions": [
          "F01"
        ],
        "situation": "S34",
        "cefr": "B1",
        "register": "R4",
        "emotions": [
          "E09"
        ],
        "expression_types": [
          "X08"
        ],
        "vibe": "V10",
        "power": [],
        "grammar_intent": [],
        "flags": []
      }
    },
    {
      "id": "ISJpKRTkvpc-21",
      "en": "Sure would love to come from head.",
      "ko": "구강 성교로 오고 싶어.",
      "tags": {
        "functions": [
          "F07"
        ],
        "situation": "S34",
        "cefr": "A2",
        "register": "R4",
        "emotions": [
          "E11"
        ],
        "expression_types": [
          "X08"
        ],
        "vibe": "V10",
        "power": [],
        "grammar_intent": [],
        "flags": []
      }
    },
    {
      "id": "ISJpKRTkvpc-22",
      "en": "Seems nobody around here has what it takes.",
      "ko": "여기서는 그런 걸 할 수 있는 사람이 없는 것 같아.",
      "tags": {
        "functions": [
          "F01"
        ],
        "situation": "S34",
        "cefr": "A2",
        "register": "R4",
        "emotions": [
          "E09"
        ],
        "expression_types": [
          "X08"
        ],
        "vibe": "V10",
        "power": [],
        "grammar_intent": [],
        "flags": []
      }
    }
  ],
  "transcriptHash": "6eada35d5d5a06c9"
}
