{
  "videoId": "PJlmYh27MHg",
  "category": "movie",
  "title": "Welcome to Jurassic Park",
  "seriesId": "jurassic-park",
  "sentenceCount": 4,
  "taggedCount": 4,
  "sentences": [
    {
      "id": "PJlmYh27MHg-0",
      "en": "Alan, this species of Veriformans has been extinct since the Cretaceous period.",
      "ko": "앨런, 이 종류의 베리포르만스는 백악기부터 멸종했어.",
      "tags": {
        "functions": [
          "F01"
        ],
        "situation": "S43",
        "cefr": "B1",
        "register": "R4",
        "emotions": [
          "E09"
        ],
        "expression_types": [
          "X08"
        ],
        "vibe": "V18",
        "power": [],
        "grammar_intent": [],
        "flags": []
      }
    },
    {
      "id": "PJlmYh27MHg-1",
      "en": "I mean, this thing is about this big. Why? I don't know.",
      "ko": "이건 이 정도 크기야. 왜? 모르겠어.",
      "tags": {
        "functions": [
          "F50"
        ],
        "situation": "S43",
        "cefr": "B1",
        "register": "R5",
        "emotions": [
          "E09"
        ],
        "expression_types": [
          "X08"
        ],
        "vibe": "V18",
        "power": [
          "P03"
        ],
        "grammar_intent": [
          "G17",
          "G18"
        ],
        "flags": []
      }
    },
    {
      "id": "PJlmYh27MHg-2",
      "en": "Alan.",
      "ko": "앨런.",
      "tags": {
        "functions": [
          "F01"
        ],
        "situation": "S43",
        "cefr": "A2",
        "register": "R4",
        "emotions": [
          "E09"
        ],
        "expression_types": [
          "X08"
        ],
        "vibe": "V18",
        "power": [],
        "grammar_intent": [],
        "flags": [
          "is_fragment"
        ]
      }
    },
    {
      "id": "PJlmYh27MHg-3",
      "en": "It's... it's...",
      "ko": "그건... 그건...",
      "tags": {
        "functions": [
          "F01"
        ],
        "situation": "S43",
        "cefr": "A2",
        "register": "R4",
        "emotions": [
          "E09"
        ],
        "expression_types": [
          "X08"
        ],
        "vibe": "V18",
        "power": [],
        "grammar_intent": [],
        "flags": [
          "is_fragment"
        ]
      }
    }
  ],
  "transcriptHash": "bff9f3b50c50a095"
}
