{
  "videoId": "pPSua1GTUKE",
  "category": "movie",
  "title": "Elle woods tells off her ex bf",
  "seriesId": "legally-blonde",
  "sentenceCount": 1,
  "taggedCount": 1,
  "sentences": [
    {
      "id": "pPSua1GTUKE-0",
      "en": "You",
      "ko": "너",
      "tags": {
        "functions": [
          "F01"
        ],
        "situation": "S36",
        "cefr": "A1",
        "register": "R4",
        "emotions": [
          "E09"
        ],
        "expression_types": [
          "X08"
        ],
        "vibe": "V18",
        "power": [],
        "grammar_intent": [],
        "flags": [
          "is_fragment"
        ]
      }
    }
  ]
}
