{
  "videoId": "ZQ_6VUs2VCk",
  "category": "movie",
  "title": "Rushing or Dragging - Fletcher's Madness",
  "seriesId": "whiplash",
  "sentenceCount": 15,
  "taggedCount": 15,
  "sentences": [
    {
      "id": "ZQ_6VUs2VCk-0",
      "en": "Five, six, seven.",
      "ko": "다섯, 여섯, 일곱.",
      "tags": {
        "functions": [
          "F01"
        ],
        "situation": "S50",
        "cefr": "A1",
        "register": "R4",
        "emotions": [
          "E09"
        ],
        "expression_types": [
          "X08"
        ],
        "vibe": "V18",
        "power": [],
        "grammar_intent": [],
        "flags": []
      }
    },
    {
      "id": "ZQ_6VUs2VCk-1",
      "en": "Not quite my tempo. It's all good, no worries. Here we go.",
      "ko": "내 템포와는 조금 달라. 괜찮아, 걱정하지 마. 시작해.",
      "tags": {
        "functions": [
          "F01"
        ],
        "situation": "S50",
        "cefr": "A2",
        "register": "R4",
        "emotions": [
          "E06"
        ],
        "expression_types": [
          "X04"
        ],
        "vibe": "V18",
        "power": [],
        "grammar_intent": [],
        "flags": []
      }
    },
    {
      "id": "ZQ_6VUs2VCk-2",
      "en": "Five, six, seven.",
      "ko": "다섯, 여섯, 일곱.",
      "tags": {
        "functions": [
          "F01"
        ],
        "situation": "S50",
        "cefr": "A1",
        "register": "R4",
        "emotions": [
          "E09"
        ],
        "expression_types": [
          "X08"
        ],
        "vibe": "V18",
        "power": [],
        "grammar_intent": [],
        "flags": []
      }
    },
    {
      "id": "ZQ_6VUs2VCk-3",
      "en": "You're rushing.",
      "ko": "너무 서두르고 있어.",
      "tags": {
        "functions": [
          "F01"
        ],
        "situation": "S50",
        "cefr": "A1",
        "register": "R4",
        "emotions": [
          "E09"
        ],
        "expression_types": [
          "X08"
        ],
        "vibe": "V18",
        "power": [],
        "grammar_intent": [],
        "flags": [
          "is_fragment"
        ]
      }
    },
    {
      "id": "ZQ_6VUs2VCk-4",
      "en": "Here we go.",
      "ko": "시작해.",
      "tags": {
        "functions": [
          "F01"
        ],
        "situation": "S50",
        "cefr": "A1",
        "register": "R4",
        "emotions": [
          "E06"
        ],
        "expression_types": [
          "X04"
        ],
        "vibe": "V18",
        "power": [],
        "grammar_intent": [],
        "flags": []
      }
    },
    {
      "id": "ZQ_6VUs2VCk-5",
      "en": "Ready? Okay.",
      "ko": "준비됐어? 좋아.",
      "tags": {
        "functions": [
          "F01"
        ],
        "situation": "S50",
        "cefr": "A1",
        "register": "R4",
        "emotions": [
          "E06"
        ],
        "expression_types": [
          "X08"
        ],
        "vibe": "V18",
        "power": [],
        "grammar_intent": [],
        "flags": [
          "is_fragment"
        ]
      }
    },
    {
      "id": "ZQ_6VUs2VCk-6",
      "en": "Five, six, and.",
      "ko": "다섯, 여섯, 그리고.",
      "tags": {
        "functions": [
          "F01"
        ],
        "situation": "S50",
        "cefr": "A1",
        "register": "R4",
        "emotions": [
          "E09"
        ],
        "expression_types": [
          "X08"
        ],
        "vibe": "V18",
        "power": [],
        "grammar_intent": [],
        "flags": []
      }
    },
    {
      "id": "ZQ_6VUs2VCk-7",
      "en": "Dragging just a hair.",
      "ko": "조금 느려.",
      "tags": {
        "functions": [
          "F01"
        ],
        "situation": "S50",
        "cefr": "A1",
        "register": "R4",
        "emotions": [
          "E09"
        ],
        "expression_types": [
          "X08"
        ],
        "vibe": "V18",
        "power": [],
        "grammar_intent": [],
        "flags": []
      }
    },
    {
      "id": "ZQ_6VUs2VCk-8",
      "en": "Wait for my cue.",
      "ko": "내 신호를 기다려.",
      "tags": {
        "functions": [
          "F01"
        ],
        "situation": "S50",
        "cefr": "A1",
        "register": "R4",
        "emotions": [
          "E09"
        ],
        "expression_types": [
          "X08"
        ],
        "vibe": "V18",
        "power": [],
        "grammar_intent": [],
        "flags": []
      }
    },
    {
      "id": "ZQ_6VUs2VCk-9",
      "en": "Five, six, seven.",
      "ko": "다섯, 여섯, 일곱.",
      "tags": {
        "functions": [
          "F01"
        ],
        "situation": "S50",
        "cefr": "A1",
        "register": "R4",
        "emotions": [
          "E09"
        ],
        "expression_types": [
          "X08"
        ],
        "vibe": "V18",
        "power": [],
        "grammar_intent": [],
        "flags": []
      }
    },
    {
      "id": "ZQ_6VUs2VCk-10",
      "en": "Rushing.",
      "ko": "서두르고 있어.",
      "tags": {
        "functions": [
          "F01"
        ],
        "situation": "S50",
        "cefr": "A1",
        "register": "R4",
        "emotions": [
          "E09"
        ],
        "expression_types": [
          "X08"
        ],
        "vibe": "V18",
        "power": [],
        "grammar_intent": [],
        "flags": [
          "is_fragment"
        ]
      }
    },
    {
      "id": "ZQ_6VUs2VCk-11",
      "en": "Five, six, and.",
      "ko": "다섯, 여섯, 그리고.",
      "tags": {
        "functions": [
          "F01"
        ],
        "situation": "S50",
        "cefr": "A1",
        "register": "R4",
        "emotions": [
          "E09"
        ],
        "expression_types": [
          "X08"
        ],
        "vibe": "V18",
        "power": [],
        "grammar_intent": [],
        "flags": []
      }
    },
    {
      "id": "ZQ_6VUs2VCk-12",
      "en": "Dragging.",
      "ko": "느려.",
      "tags": {
        "functions": [
          "F01"
        ],
        "situation": "S50",
        "cefr": "A1",
        "register": "R4",
        "emotions": [
          "E09"
        ],
        "expression_types": [
          "X08"
        ],
        "vibe": "V18",
        "power": [],
        "grammar_intent": [],
        "flags": [
          "is_fragment"
        ]
      }
    },
    {
      "id": "ZQ_6VUs2VCk-13",
      "en": "Five, six, and.",
      "ko": "다섯, 여섯, 그리고.",
      "tags": {
        "functions": [
          "F01"
        ],
        "situation": "S50",
        "cefr": "A1",
        "register": "R4",
        "emotions": [
          "E09"
        ],
        "expression_types": [
          "X08"
        ],
        "vibe": "V18",
        "power": [],
        "grammar_intent": [],
        "flags": []
      }
    },
    {
      "id": "ZQ_6VUs2VCk-14",
      "en": "Dragging.",
      "ko": "느려.",
      "tags": {
        "functions": [
          "F01"
        ],
        "situation": "S50",
        "cefr": "A1",
        "register": "R4",
        "emotions": [
          "E09"
        ],
        "expression_types": [
          "X08"
        ],
        "vibe": "V18",
        "power": [],
        "grammar_intent": [],
        "flags": [
          "is_fragment"
        ]
      }
    }
  ],
  "transcriptHash": "a617cc61f4d3fe06"
}
